{"ar":{"Paperback":"غلاف ورقي","Hardback":"تجليد فني","Journal":"دورية","Magazine":"مجلة","Politics":"سياسة","Religion":"دين","Novel":"رواية","Dictionary":"معجم","Capitalism":"رأسمالية","Graded Reader":"مختصرة على مستويات","Foreign Language Study":"تعلم اللغات الأجنبية","Sinology":"دراسات صينية","Philosophy":"فلسفة","Science":"علوم","Mathematics":"رياضيات","Artificial Intelligence":"ذكاء صنعي","Play":"مسرح","Performing Arts":"فنون تعبيرية","General":"عام","Poetry":"شعر","Linguistics":"لسانيات","Turkish":"لغة تركية","Physics":"فيزياء","Logic":"منطق","Computers":"حواسب","Machine Theory":"نظرية الآلة","Literature":"أدب","Sophism":"صوفية","Turkish Literature":"أدب تركي","Algebra":"جبر","Calculus":"تفاضل وتكامل","Geometry":"هندسة","Autobiography":"سيرة ذاتية","Biography & Autobiography":"سيرة","English as a Second Language":"الإنگليزية لغةً ثانية","Language Arts & Disciplines":"فنون اللغة","Sociology":"علم اجتماع","Russian Literature":"أدب روسي","Classics":"كلاسيكيات","Russia":"روسيا","Philosophy of Science":"فلسفة العلوم","Diaries":"يوميات","Economics":"اقتصاد","Iranian literature":"أدب إيراني","Short Stories":"قصص قصيرة","Biography":"سيرة","Memoirs":"مذكرات","Encyclopedia":"موسوعة","Psychology":"علم نفس","Letters":"مراسلات","Romance":"حب","Geography":"جغرافية","Farsi":"فارسية","Iranian History":"تاريخ إيران","Meditations":"تأملات","Speeches":"خطابات","Essays":"مقالات","Language Learning":"تعليم لغات","India":"الهند","Philosophy of History":"فلسفة التاريخ","History Sudies":"دراسات تاريخية","French Literature":"أدب فرنسي","Islamic Studies":"دراسات إسلامية","Self-Help":"تطوير ذاتي","Probabilites":"احتمالات","Statistics":"إحصاء","Women's liberation":"تحرير المرأة","Feminism":"نسوية"}}